{
  "resources": [
    {
      "path": "data.csv",
      "name": "data",
      "profile": "tabular-data-resource",
      "scheme": "file",
      "format": "csv",
      "hashing": "md5",
      "encoding": "utf-8",
      "schema": {
        "fields": [
          {
            "name": "Year",
            "type": "integer"
          },
          {
            "name": "Units",
            "type": "string",
            "constraints": {
              "enum": [
                "%",
                ""
              ]
            }
          },
          {
            "name": "Administrative head",
            "type": "string",
            "constraints": {
              "enum": [
                "1.0",
                "2.0",
                "3.0",
                "4.0",
                "5.0",
                "6.0",
                "7.0",
                "8.0",
                "9.0",
                "10.0",
                ""
              ]
            }
          },
          {
            "name": "Summary sheet 1",
            "type": "string",
            "constraints": {
              "enum": [
                "pi_1",
                "pi_2",
                "share_of_budget",
                ""
              ]
            }
          },
          {
            "name": "Economic head",
            "type": "string",
            "constraints": {
              "enum": [
                "compensation_employees",
                "goods_services",
                "fixed_capital",
                "interest",
                "subsidies",
                "grants",
                "social_benefits",
                "other_expenses",
                ""
              ]
            }
          },
          {
            "name": "Summary sheet 2",
            "type": "string",
            "constraints": {
              "enum": [
                "composition_variance",
                ""
              ]
            }
          },
          {
            "name": "Category",
            "type": "string",
            "constraints": {
              "enum": [
                "16_6_1_cat_1",
                ""
              ]
            }
          },
          {
            "name": "Value",
            "type": "number"
          }
        ]
      }
    }
  ],
  "profile": "data-package",
  "name": "16-6-1",
  "title": "Primary government expenditures as a proportion of original approved budget, by sector (or by budget codes or similar)"
}