{"computation_units":"Percentage","data_non_statistical":false,"data_show_map":false,"data_start_values":[],"expected_disaggregations":[],"graph_title":"Obim doznaka (u ameri\u010dkim dolarima) kao proporcija ukupnog BDP-a","graph_titles":[],"graph_type":"line","indicator_name":"Obim doznaka (u ameri\u010dkim dolarima) kao proporcija ukupnog BDP-a","indicator_number":"17.3.2","national_geographical_coverage":"Crna Gora","precision":[{"unit":"data.percentage"},{"decimals":2}],"reporting_status":"complete","standalone":false,"SDG_GOAL__GLOBAL":"Unaprijediti sredstva za sprovo\u0111enje i obnoviti Globalno partnerstvo za odr\u017eivi razvoj","SDG_TARGET__GLOBAL":"Mobilisati dodatna finansijska sredstva za zemlje u razvoju iz vi\u0161e izvora","SDG_INDICATOR__GLOBAL":"Obim doznaka (u ameri\u010dkim dolarima) kao proporcija ukupnog BDP-a","methodology_global":"","SDG_GOAL":"Unaprijediti sredstva za sprovo\u0111enje i obnoviti Globalno partnerstvo za odr\u017eivi razvoj","SDG_TARGET":"Mobilisati dodatna finansijska sredstva za zemlje u razvoju iz vi\u0161e izvora","SDG_INDICATOR":"Obim doznaka (u ameri\u010dkim dolarima) kao proporcija ukupnog BDP-a","methodology_national":"","DATA_SOURCE":"UNECE: https://w3.unece.org/SDG/","COVERAGE":"","REC_USE_LIM":"Podaci su prikupljeni do 1. maja 2023. godine.","COMPARABILITY":"","methodology_start_date":"","indicator_introduction_plan":"","source_active_1":true,"source_organisation_1":"Centralna banka Crne Gore","national_metadata_updated_date":"2023-07-10","national_data_updated_date":"2023-07-10","target_number":"17.3","goal_number":"17","indicator_sort_order":"17-03-02"}