{"computation_units":"Percentage","data_non_statistical":false,"data_show_map":false,"data_start_values":[],"expected_disaggregations":[],"graph_title":"Kapacitet me\u0111unarodnih zdravstvenih propisa (IHR) i spremnost za hitne zdravstvene situacije","graph_titles":[],"graph_type":"bar","indicator_name":"Kapacitet me\u0111unarodnih zdravstvenih propisa (IHR) i spremnost za hitne zdravstvene situacije","indicator_number":"3.d.1","national_geographical_coverage":"Crna Gora","precision":[{"unit":"percentage"},{"decimals":2}],"reporting_status":"complete","standalone":false,"SDG_GOAL__GLOBAL":"global_goals.3-titletitle","SDG_TARGET__GLOBAL":"Osna\u017eiti kapacitete svih zemalja, a posebno zemalja u razvoju, za rano upozorenje, smanjenje rizika i upravljanje nacionalnim i globalnim zdravstvenim rizicima","SDG_INDICATOR__GLOBAL":"Kapacitet me\u0111unarodnih zdravstvenih propisa (IHR) i spremnost za hitne zdravstvene situacije","methodology_global":"","SDG_GOAL":"Obezbijediti zdrave \u017eivote i promovisati dobrobit za sve ljude u svim uzrastima","SDG_TARGET":"Osna\u017eiti kapacitete svih zemalja, a posebno zemalja u razvoju, za rano upozorenje, smanjenje rizika i upravljanje nacionalnim i globalnim zdravstvenim rizicima","SDG_INDICATOR":"Kapacitet me\u0111unarodnih zdravstvenih propisa (IHR) i spremnost za hitne zdravstvene situacije","methodology_national":"","DATA_SOURCE":"UNECE: https://w3.unece.org/SDG/","COVERAGE":"","REC_USE_LIM":"Podaci su prikupljeni do 1. maja 2023. godine.","COMPARABILITY":"","methodology_start_date":"","indicator_introduction_plan":"","source_active_1":true,"source_organisation_1":"Institut za javno zdravlje Crne Gore","national_metadata_updated_date":"2023-07-09","national_data_updated_date":"2023-07-09","target_number":"3.d","goal_number":"3","indicator_sort_order":"03-0d-01"}